LICENSE
MANIFEST.in
README.md
setup.cfg
setup.py
examples/application_basic/README.md
examples/application_basic/command.py
examples/c++_ipc/Makefile
examples/c++_ipc/README.org
examples/c++_ipc/cppmain.cc
examples/c++_ipc/ipc-client
examples/c++_ipc/ipc-client.py
examples/c++_ipc/ipc-server.py
examples/c++_ipc/ipcmsg.pb.cc
examples/c++_ipc/ipcmsg.pb.h
examples/c++_ipc/ipcmsg.proto
examples/c++_ipc/ipcmsg_pb2.py
examples/c++_ipc/ipcmsg_pb2.pyc
examples/hal_basic/README.md
examples/hal_basic/anddemo.py
examples/logger/README.md
examples/logger/logger.py
examples/ncurses/README.md
examples/ncurses/ncurses.py
examples/ncurses/test.ngc
examples/ncurses/ngc/test.ngc
examples/testing/README.md
examples/testing/broken_messages.py
examples/testing/halremote.py
examples/zeroconf/test.py
pymachinetalk/__init__.py
pymachinetalk/common.py
pymachinetalk/dns_sd.py
pymachinetalk/halremote.py
pymachinetalk.egg-info/PKG-INFO
pymachinetalk.egg-info/SOURCES.txt
pymachinetalk.egg-info/dependency_links.txt
pymachinetalk.egg-info/namespace_packages.txt
pymachinetalk.egg-info/requires.txt
pymachinetalk.egg-info/top_level.txt
pymachinetalk/application/__init__.py
pymachinetalk/application/command.py
pymachinetalk/application/constants.py
pymachinetalk/application/error.py
pymachinetalk/application/file.py
pymachinetalk/application/log.py
pymachinetalk/application/status.py
pymachinetalk/application/tests/__init__.py
pymachinetalk/application/tests/test_integration.py
pymachinetalk/machinetalk_core/__init__.py
pymachinetalk/machinetalk_core/application/__init__.py
pymachinetalk/machinetalk_core/application/commandbase.py
pymachinetalk/machinetalk_core/application/commandservicebase.py
pymachinetalk/machinetalk_core/application/configbase.py
pymachinetalk/machinetalk_core/application/errorbase.py
pymachinetalk/machinetalk_core/application/errorservicebase.py
pymachinetalk/machinetalk_core/application/errorsubscribe.py
pymachinetalk/machinetalk_core/application/launcherbase.py
pymachinetalk/machinetalk_core/application/launchersubscribe.py
pymachinetalk/machinetalk_core/application/logbase.py
pymachinetalk/machinetalk_core/application/logserver.py
pymachinetalk/machinetalk_core/application/logservicebase.py
