Metadata-Version: 2.1
Name: pymachinetalk
Version: 0.13.1
Summary: Python bindings for Machinetalk
Home-page: https://github.com/machinekit/pymachinetalk
Author: Alexander Roessler
Author-email: alex@machinekoder.com
License: UNKNOWN
Platform: UNKNOWN
Provides-Extra: dev
